vedro_fn/__init__.py
vedro_fn/_scenario_decorator.py
vedro_fn/_scenario_descriptor.py
vedro_fn/_scenario_loader.py
vedro_fn/_scenario_steps.py
vedro_fn/_vedro_fn_plugin.py
vedro_fn/py.typed
vedro_fn-0.1.2.dist-info/licenses/LICENSE
vedro_fn-0.1.2.dist-info/METADATA
vedro_fn-0.1.2.dist-info/WHEEL
vedro_fn-0.1.2.dist-info/top_level.txt
vedro_fn-0.1.2.dist-info/RECORD
